Workbook

Sheet Summary
A1: Focus Legacy - Use Case Test Report
A3: Test date | B3: 2026-09-29
A4: System under test | B4: Megh One AI - pipeline.answer_question (the function behind POST /api/query), run in-process against the live megh_db, the vLLM gateway and the Qdrant knowledge base
A5: Use cases | B5: Use_Cases_-_Focus.csv: 28 use cases (TC-01 to TC-28). Two supplementary probes (TC-14b, TC-28blk) are shown but not counted.
A6: Compared against | B6: (1) the live DB view curated.v_focus_legacy (+ curated.dim_geography for constituency); (2) the raw file 'Focus Legacy to share to BLH.csv' (14,569 rows); (3) the knowledge base (data/reference/FOCUS_LEGACY_FAQ.md, FOCUS_legacy_Complete_Reference.md) for the descriptive questions TC-01 to TC-09. Expected values were computed independently from the DB and from the raw file.
A7: Method | B7: Each question was asked as written in the use-case file. Where the bot asked a clarification, the chip an officer would pick was clicked ('Focus Legacy'; 'All of Meghalaya'; 'All financial years combined'; 'assembly constituency' for TC-28). Placeholders: [pg_name] = Bak 15 Banana Dijogre; top 5 / more than 15 members; [district] = West Garo Hills (TC-17), East Khasi Hills (TC-18), West Khasi Hills (TC-26); Rs 1,00,000; FY 2022-23; [village] = Abima; [constituency] = Songsak. The whole set was run 3 times; a case PASSES only if every run is correct and the tester's manual review agrees.
A8: Pass rule | B8: PASS = the bot's final answer agrees with the DB and the raw file (or the KB for descriptive questions) and does not mislead. FAIL = a wrong or missing figure, the wrong route, or a correct figure presented misleadingly.
A10: RESULTS (28 use cases)
A11: Total | B11: =COUNTIFS('Test Results'!A2:A31,"TC-??") -> 28
A12: Passed | B12: =COUNTIFS('Test Results'!A2:A31,"TC-??",'Test Results'!P2:P31,"PASS") -> 28
A13: Failed | B13: =COUNTIFS('Test Results'!A2:A31,"TC-??",'Test Results'!P2:P31,"FAIL") -> 0
A14: Pass rate | B14: =IF(B11=0,0,B12/B11) -> 1
A15: Supplementary (not counted) | B15: =COUNTIFS('Test Results'!A2:A31,"TC-*?*",'Test Results'!P2:P31,"PASS")-B12&" of 2 passed (TC-14b, TC-28blk)" -> 2 of 2 passed (TC-14b, TC-28blk)
A16: DB vs Raw checks | B16: =COUNTIF('DB vs Raw Reconciliation'!E4:E58,"MATCH")&" MATCH, "&COUNTIF('DB vs Raw Reconciliation'!E4:E58,"BY DESIGN")&" by design, "&COUNTIF('DB vs Raw Reconciliation'!E4:E58,"MISMATCH")&" MISMATCH, of "&COUNTA('DB vs Raw Reconciliation'!A4:A58) -> 54 MATCH, 1 by design, 0 MISMATCH, of 55
A18: OBSERVATIONS (not failures)
A19: Obs 1 | B19: DB and raw file agree row for row: 14,569 rows joined on id = source_row_id; pg_id, members, amount, date, financial year, district, block, village and constituency are identical on every row. The only difference is PG name spelling on 1,636 rows: the DB keeps one current name per pg_id (by design).
A20: Obs 2 | B20: Money is printed as stored in some answers (e.g. '54205000.00', '114990000.00'), without Rs or Indian digit grouping (TC-18, TC-23).
A21: Obs 3 | B21: TC-21 names months as 'month 4 / month 5' instead of April 2022 / May 2022.
A22: Obs 4 | B22: TC-26: 5 West Khasi Hills PGs have no block in the source (raw and DB). The bot lists the 5 blocks correctly but does not mention these 5, and calls 921 the total 'across all blocks' (district total 926).
A23: Obs 5 | B23: TC-10 / TC-16: 'beneficiaries' / 'PG members' = sum of members over all 14,569 payments (102,021). A PG paid twice counts twice; counting each PG once gives 91,446. The data has no member-level IDs; an SME should confirm which definition officers expect.
A24: Obs 6 | B24: TC-15: one PG (Nongprat Lynti) records 190 members; every other PG has 20 or fewer. Same in the raw file - a possible source-data entry error for the data team to confirm.
A25: Obs 7 | B25: TC-28: the whole-constituency chip says '190 villages in the employment data' (MGNREGA wording) in a Focus Legacy conversation. Cosmetic.
A26: Obs 8 | B26: A bare 'FOCUS' asks 'Focus Legacy or Focus Plus?' first. This is intended (two schemes share the name), and adds one click to TC-01..10.
A28: Sheets | B28: Test Results - one row per case: question, clarifications clicked, bot answer, SQL, bot figure vs DB vs raw, result of each of the 3 runs, final result, reason, and a link to its proof. DB vs Raw Reconciliation - aggregate and row-level comparison of the DB with the raw file. Proof Screenshots - one capture per case of the full conversation, the SQL the bot ran, and the DB/raw verification. The same PNGs are in docs/Focus_Legacy_UseCase_Evidence_2026-09-29/.
A29: Privacy | B29: The raw file contains unmasked bank account numbers and holder names. Neither was read into or shown in this report: only aggregates, PG ids and PG names are used.

Sheet Test Results
A1: Test Case | B1: Use Case | C1: Question asked (as in the use-case file, placeholders filled) | D1: Clarifications (chip clicked) | E1: Bot route | F1: Bot answer (final turn) | G1: SQL run by bot | H1: Bot figure | I1: Expected - DB (live) | J1: Expected - Raw CSV | K1: Bot vs DB | L1: Bot vs Raw | M1: Run 1 | N1: Run 2 | O1: Run 3 | P1: RESULT | Q1: Reason / remarks | R1: Proof
A2: TC-01 | B2: Understand the FOCUS scheme | C2: What is the FOCUS scheme in Meghalaya? | D2: 1: Focus Legacy (producer group payments) | E2: knowledge | F2: The Focus Legacy scheme (FOCUS) is a flagship farmer-welfare and agri-economic programme of the Government of Meghalaya designed to upscale farming activity and raise farmer incomes. - FOCUS (Farmers' Collectivization for Upscaling Production and Marketing Systems) - A flagship scheme that organizes farmers into Producer Groups to receive direct financial assistance and value-chain support. - Producer Groups (PGs) - Grassroots collectives (rural and urban) through which members access and pool scheme funds. - Government of Meghalaya, Office of the Chief Minister - Drives flagship launches and major cheque-distribution events, led by Chief Minister Conrad K. Sangma. - Department of Agriculture and Farmers' Empowerment - The nodal department for agricultural components and Mission Mode projects. - Community & Rural Development (C&RD) Blocks - Block-level administrative units coordinating registration, verification, and local rollout. - MeghalayaOne portal - The state's digital citizen-services portal used for registration and status tracking. - MyMeg portal - A portal listing FOCUS scheme details by sector, district, and block. The scheme was conceived partly in response to economic hardship during the COVID-19 pandemic and is implemented through Direct Benefit Transfer (DBT) or cheque disbursement to registered Producer Groups. | H2: Descriptive (knowledge base) | I2: n/a - descriptive question | J2: n/a - descriptive question | K2: n/a | L2: n/a | M2: PASS | N2: PASS | O2: PASS | P2: PASS | Q2: All statements match the KB (full form, PG model, C&RD blocks, MeghalayaOne/MyMeg portals, COVID-19 origin, cheque/DBT). Bot first asks 'Focus Legacy or Focus Plus?' (intended - two schemes are named Focus). | R2: View proof
A3: TC-02 | B3: Understand the scheme objective | C3: What is the main objective of FOCUS? | D3: 1: Focus Legacy (producer group payments) | E3: knowledge | F3: The main objective of Focus Legacy (FOCUS) is to upscale farming and income-generating activities by organizing farmers into collectives and providing direct financial and value-chain support. - Upscaling production and marketing - Organizing farmers into Producer Groups to increase farming activity and market linkages. - Raising farmer incomes - Providing direct financial assistance and value-chain support to improve economic outcomes for members. - Strengthening market linkages - Facilitating efficient movement of produce from farm to market through aggregation and transportation support. - Supporting high-value sectors - Focusing on specific Mission Mode sub-sectors like Lakadong turmeric, piggery, dairy, spices, ginger, aroma crops, poultry, and horticulture. - Promoting financial inclusion - Delivering grants rather than loans to help members use funds as seed or working capital. | H3: Descriptive (knowledge base) | I3: n/a - descriptive question | J3: n/a - descriptive question | K3: n/a | L3: n/a | M3: PASS | N3: PASS | O3: PASS | P3: PASS | Q3: Objective matches the KB (upscaling production & marketing, incomes, market linkages, Mission Mode sectors, grant not loan). | R3: View proof
A4: TC-03 | B4: Understand beneficiary eligibility | C4: Who can benefit under the FOCUS scheme? | D4: 1: Focus Legacy (producer group payments) | E4: knowledge | F4: The primary eligible units under the Focus Legacy scheme are farmers organized into Producer Groups, with specific eligibility expanding to include the following categories: - Rural farming households - the original target group across Meghalaya organized into Producer Groups. - Urban Producer Groups - groups of 10 or more members engaged in a shared income-generating activity (e.g., weaving, pickle-making, or youth enterprise) available from October 2022. Each eligible Producer Group member receives an initial mobilisation fund of Rs 5,000 to upscale their existing farming or income-generating activity. | H4: Descriptive (knowledge base) | I4: n/a - descriptive question | J4: n/a - descriptive question | K4: n/a | L4: n/a | M4: PASS | N4: PASS | O4: PASS | P4: PASS | Q4: Eligibility matches the KB exactly (rural households, urban PGs of 10 or more members from October 2022, Rs 5,000 per member). | R4: View proof
A5: TC-04 | B5: Understand Producer Groups | C5: What is the role of Producer Groups under FOCUS? | D5: 0 | E5: knowledge | F5: Under the FOCUS scheme, Producer Groups (PGs) serve as the primary eligible unit and the core organizing mechanism for delivering financial and value-chain support to farmers and income-generating individuals. - Primary eligible unit - Farmers organized into groups (or willing to form them) are the main target for receiving scheme benefits. - Collectivisation model - PGs allow individuals to access benefits collectively, even though cash assistance is credited directly to each member. - Urban eligibility extension - Since October 2022, urban groups of 10+ members engaged in shared income activities (e.g., weaving, pickle-making) are eligible alongside rural farming households. - Channel for assistance - PGs are the vehicle through which the government provides initial mobilisation funds, value-chain support, and market linkages to upscaling activities. - Implementation structure - PG formation and benefit distribution are managed through Community & Rural Development (C&RD) Blocks across the state. | H5: Descriptive (knowledge base) | I5: n/a - descriptive question | J5: n/a - descriptive question | K5: n/a | L5: n/a | M5: PASS | N5: PASS | O5: PASS | P5: PASS | Q5: Role of PGs matches the KB (primary eligible unit, benefit credited to members, urban extension, C&RD blocks). Answered directly - no clarification needed. | R5: View proof
A6: TC-05 | B6: Understand financial assistance | C6: What type of financial assistance is provided under FOCUS? | D6: 1: Focus Legacy (producer group payments) | E6: knowledge | F6: The financial assistance under Focus Legacy is provided as a non-repayable grant rather than a loan, with specific support types including: - Initial mobilisation fund - A one-time cash grant of Rs 5,000 per Producer Group member intended as seed or working capital. - Revolving fund mechanism - An optional arrangement where groups circulate part of the funds among members to ensure benefits recirculate within the group. - Value-chain development support - Assistance for funding, machinery, market linkages, transportation, and aggregation of produce to move output efficiently from farm to market. | H6: Descriptive (knowledge base) | I6: n/a - descriptive question | J6: n/a - descriptive question | K6: n/a | L6: n/a | M6: PASS | N6: PASS | O6: PASS | P6: PASS | Q6: Matches the KB: non-repayable grant, Rs 5,000 per member, revolving fund, value-chain support. | R6: View proof
A7: TC-06 | B7: Understand scheme support provided to Producer Groups | C7: What kind of support does FOCUS provide to Producer Groups? | D7: 0 | E7: knowledge | F7: FOCUS provides comprehensive support to Producer Groups to enhance their farming and income-generating activities through the following mechanisms: - Value-chain development - assistance to improve the entire process from production to market. - Machinery support - provision of equipment to aid agricultural or income-generating operations. - Market linkages - facilitation of connections between producers and buyers. - Transportation - support for moving produce efficiently from farm to market. - Aggregation of produce - consolidation of output to streamline marketing and sales. - Initial mobilisation fund - a one-time seed/working capital grant of Rs 5,000 per member. - Financial assistance - direct funding to upscale farming and income-generating activities. | H7: Descriptive (knowledge base) | I7: n/a - descriptive question | J7: n/a - descriptive question | K7: n/a | L7: n/a | M7: PASS | N7: PASS | O7: PASS | P7: PASS | Q7: All support types listed are in the KB. | R7: View proof
A8: TC-07 | B8: Understand fund distribution | C8: How is financial assistance distributed under FOCUS? | D8: 1: Focus Legacy (producer group payments) | E8: knowledge | F8: Financial assistance under Focus Legacy is distributed as a non-repayable grant rather than a loan, with the primary cash component being an initial mobilisation fund of Rs 5,000 credited to each Producer Group member. - Nature of assistance - An outright grant that does not require repayment. - Initial cash mobilisation - Rs 5,000 per Producer Group member intended as seed/working capital. - Revolving fund mechanism - Groups may circulate part of the funds among members to ensure benefits recirculate within the group. - Disbursal methods - Delivered via cheques at public distribution events or through direct bank transfers (DBT). - Administrative oversight - Managed and distributed through Community & Rural Development (C&RD) Blocks. - Additional support - Includes value-chain development, machinery support, market linkages, transportation, and aggregation of produce. | H8: Descriptive (knowledge base) | I8: n/a - descriptive question | J8: n/a - descriptive question | K8: n/a | L8: n/a | M8: PASS | N8: PASS | O8: PASS | P8: PASS | Q8: Distribution mechanism matches the KB (cheques at public events + DBT, via C&RD blocks, Rs 5,000 per member). | R8: View proof
A9: TC-08 | B9: Understand scheme coverage | C9: How many Producer Groups have been covered under FOCUS? | D9: 2: All of Meghalaya > All financial years combined | E9: data | F9: 11,906 Producer Groups have been covered under FOCUS for all of Meghalaya across all financial years. | G9: SELECT COUNT(DISTINCT pg_id) AS producer_groups FROM curated.v_focus_legacy LIMIT 1000000 | H9: 11,906 PGs | I9: 11,906 distinct pg_id | J9: 11,906 distinct pg_id | K9: MATCH | L9: MATCH | M9: PASS | N9: PASS | O9: PASS | P9: PASS | Q9: Correct. Bot asked scope (All of Meghalaya) and year (all years) before answering. | R9: View proof
A10: TC-09 | B10: Get a scheme overview for official briefing | C10: Give me a short overview of FOCUS that I can use for an official briefing. | D10: 1: Focus Legacy (producer group payments) | E10: knowledge | F10: Focus Legacy, officially known as the FOCUS scheme (Farmers' Collectivization for Upscaling Production and Marketing Systems), is a flagship farmer-welfare initiative of the Government of Meghalaya designed to organize farmers into Producer Groups for financial and value-chain support. - Producer Groups (PGs) - Farmer collectives eligible for direct financial assistance and value-chain support to upscale farming and income-generating activities. - Initial Mobilisation Fund - A seed/working capital of Rs 5,000 provided to each member to upscale existing activities. - Revolving Fund - A mechanism encouraged by the Chief Minister to circulate funds among members rather than as a one-time payout. - Mission Mode Sectors - High-value agricultural sub-sectors including Lakadong turmeric, piggery, milk/dairy, spices, ginger, aroma crops, and poultry/horticulture. - Eligible Units - Rural farming households and urban Producer Groups of 10+ members engaged in shared income-generating activities. - Government Association - Closely linked to Chief Minister Conrad K. Sangma, who leads major cheque-distribution events across the state. This scheme serves as the foundational program for related state initiatives and aims to strengthen market linkages and raise farmer incomes. | H10: Descriptive (knowledge base) | I10: n/a - descriptive question | J10: n/a - descriptive question | K10: n/a | L10: n/a | M10: PASS | N10: PASS | O10: PASS | P10: PASS | Q10: A concise, briefing-ready overview; every point is in the KB (earlier rounds wrongly returned a list of institutions - fixed). | R10: View proof
A11: TC-10 | B11: Identify total beneficiaries in the FOCUS scheme | C11: How many total beneficiaries are available under the FOCUS scheme? | D11: 3: Focus Legacy (producer group payments) > All of Meghalaya > All financial years combined | E11: data | F11: The total number of beneficiaries under the Focus Legacy scheme for all of Meghalaya across all financial years is 102,021. | G11: SELECT SUM(no_of_pg_members) AS beneficiaries FROM curated.v_focus_legacy LIMIT 1 | H11: 102,021 beneficiaries | I11: 102,021 = SUM(no_of_pg_members) over 14,569 payments | J11: 102,021 = SUM(no_of_pg_members) | K11: MATCH | L11: MATCH | M11: PASS | N11: PASS | O11: PASS | P11: PASS | Q11: Correct against DB and raw. Remark: 'beneficiaries' is the sum of members over all payments; a PG paid twice counts its members twice. Counting each PG once at its largest size gives 91,446 (DB = raw). The file has no member-level IDs, so unique persons cannot be counted. | R11: View proof
A12: TC-11 | B12: Identify unique Producer Groups | C12: How many unique Producer Groups are present under FOCUS scheme? | D12: 2: All of Meghalaya > All financial years combined | E12: data | F12: There are 11,906 unique Producer Groups under the FOCUS scheme for all of Meghalaya across all financial years. | G12: SELECT COUNT(DISTINCT pg_id) AS producer_groups FROM curated.v_focus_legacy | H12: 11,906 unique PGs | I12: 11,906 | J12: 11,906 | K12: MATCH | L12: MATCH | M12: PASS | N12: PASS | O12: PASS | P12: PASS | Q12: Correct. | R12: View proof
A13: TC-12 | B13: Identify duplicate Producer Groups | C13: Are there any duplicate Producer Groups there? | D13: 0 | E13: data | F13: The dataset includes 11,906 producer groups with 14,569 total payments, where 2,655 groups were paid more than once and 0 duplicate payment records exist. | G13: SELECT COUNT(DISTINCT pg_id) AS producer_groups, COUNT(*) AS payments, (SELECT COUNT(*) FROM (SELECT pg_id FROM curated.v_focus_legacy GROUP BY pg_id HAVING COUNT(*) > 1) r) AS groups_paid_more_than_once, (SELECT COUNT(*) FROM (SELECT pg_id, date_of_remittance FROM curated.v_focus_legacy GROUP BY pg_id, date_of_remittance HAVING COUNT(*) > 1) d) AS duplicate_payment_records FROM curated.v_focus_legacy LIMIT 1000 | H13: 0 duplicate payment records; 2,655 PGs paid more than once; 11,906 PGs / 14,569 payments | I13: 0 exact duplicate rows; 2,655 pg_id with >1 payment; 11,906 / 14,569 | J13: 0 exact duplicate rows; 2,655 pg_id with >1 payment; 11,906 / 14,569 | K13: MATCH | L13: MATCH | M13: PASS | N13: PASS | O13: PASS | P13: PASS | Q13: Correct and not misleading: repeat-paid groups are distinguished from true duplicate records (0). | R13: View proof
A14: TC-13 | B14: Search for a Producer Group by name | C14: Is there any Producer Group named Nongstoin PG? | D14: 0 | E14: data | F14: No producer group named "Nongstoin PG" was found in the Focus Legacy data (names are matched on their words, ignoring "PG" / "Producer Group"). | G14: SELECT pg_id, MAX(pg_name) AS pg_name, MAX(lgd_district) AS district, MAX(lgd_block) AS block, MAX(no_of_pg_members) AS group_size, MIN(no_of_pg_members) AS smallest_recorded_size, COUNT(*) AS payments, SUM(amount_disbursed) AS amount_disbursed FROM curated.v_focus_legacy WHERE pg_name ~* '\mnongstoin' GROUP BY pg_id ORDER BY pg_id LIMIT 1000 | H14: No PG named 'Nongstoin PG' | I14: 0 PG names contain 'Nongstoin' | J14: 0 PG names contain 'Nongstoin' | K14: MATCH | L14: MATCH | M14: PASS | N14: PASS | O14: PASS | P14: PASS | Q14: Correct - no such group exists in either source ('Nongstoin' is a block name, 460 PGs are in that block). | R14: View proof
A15: TC-14 | B15: Check the number of members in a Producer Group | C15: How many members are there in Bak 15 Banana Dijogre? | D15: 1: Focus Legacy (producer group payments) | E15: data | F15: Bak 15 Banana Dijogre (PG-FOCUS-EGH-2115, Songsak block, East Garo Hills) has 12 members. | G15: SELECT pg_id, MAX(pg_name) AS pg_name, MAX(lgd_district) AS district, MAX(lgd_block) AS block, MAX(no_of_pg_members) AS group_size, MIN(no_of_pg_members) AS smallest_recorded_size, COUNT(*) AS payments, SUM(amount_disbursed) AS amount_disbursed FROM curated.v_focus_legacy WHERE pg_name ~* '\mbak\M' AND pg_name ~* '\m15\M' AND pg_name ~* '\mbanana\M' AND pg_name ~* '\mdijogre\M' GROUP BY pg_id ORDER BY pg_id LIMIT 1000 | H15: Bak 15 Banana Dijogre: 12 members (PG-FOCUS-EGH-2115, Songsak block, East Garo Hills) | I15: 12 | J15: 12 | K15: MATCH | L15: MATCH | M15: PASS | N15: PASS | O15: PASS | P15: PASS | Q15: Correct. [pg_name] filled with a real PG. Bot asked which scheme (PG name alone does not name the scheme). | R15: View proof
A16: TC-14b | B16: Supplementary: members of a PG that was paid twice | C16: How many members are there in Umtyrkhow Pg? | D16: 0 | E16: data | F16: Umtyrkhow Pg (PG-FOCUS-EKH-2613, Mawryngkneng block, East Khasi Hills) has 20 members. | G16: SELECT pg_id, MAX(pg_name) AS pg_name, MAX(lgd_district) AS district, MAX(lgd_block) AS block, MAX(no_of_pg_members) AS group_size, MIN(no_of_pg_members) AS smallest_recorded_size, COUNT(*) AS payments, SUM(amount_disbursed) AS amount_disbursed FROM curated.v_focus_legacy WHERE pg_name ~* '\mumtyrkhow\M' GROUP BY pg_id ORDER BY pg_id LIMIT 1000 | H16: Umtyrkhow Pg: 20 members | I16: 20 (paid twice, 20 members each time) | J16: 20 (2 rows x 20) | K16: MATCH | L16: MATCH | M16: PASS | N16: PASS | O16: PASS | P16: PASS | Q16: Supplementary (not counted): a PG paid twice is reported at its group size (20), not summed (40). | R16: View proof
A17: TC-15 | B17: Identify Producer Groups based on member count | C17: List top 5 PGs which has more than 15 members. | D17: 1: All financial years combined | E17: data | F17: 1,047 producer groups match the criteria, with the top five being Nongprat Lynti, Shinning Producer Group, Chedilgen Pg, Bak 13 Bansam Ading Producer Group, and Bak 13 Orange Producer Group. These groups have sizes of 190, 20, 20, 20, and 20 respectively. | G17: SELECT pg_id, MAX(pg_name) AS pg_name, lgd_district, MAX(no_of_pg_members) AS group_size FROM curated.v_focus_legacy GROUP BY pg_id, lgd_district HAVING MAX(no_of_pg_members) > 15 ORDER BY group_size DESC, pg_id LIMIT 5 | H17: 1,047 PGs have >15 members; top 5: Nongprat Lynti 190, Shinning Producer Group 20, Chedilgen Pg 20, Bak 13 Bansam Ading Producer Group 20, Bak 13 Orange Producer Group 20 | I17: 1,047 PGs with MAX(members)>15; max 190 (Nongprat Lynti), then many ties at 20 | J17: 1,047; 190 (Nongprat Lynti), then ties at 20 | K17: MATCH | L17: MATCH | M17: PASS | N17: PASS | O17: PASS | P17: PASS | Q17: Correct: each of the 5 named PGs was checked in DB and raw (190, 20, 20, 20, 20). Positions 2-5 are ties at 20 members, so any 4 of the 20-member PGs are valid. Remark: the 190-member PG is an outlier in the source data (all others are <= 20). | R17: View proof
A18: TC-16 | B18: Calculate the total number of Producer Group members | C18: What is the total number of PG members recorded till now? | D18: 0 | E18: data | F18: The total number of PG members recorded is 102,021. | G18: SELECT SUM(no_of_pg_members) AS memberships FROM curated.v_focus_legacy | H18: 102,021 | I18: 102,021 | J18: 102,021 | K18: MATCH | L18: MATCH | M18: PASS | N18: PASS | O18: PASS | P18: PASS | Q18: Correct (same definition remark as TC-10). | R18: View proof
A19: TC-17 | B19: Calculate total Producer Group members by district | C19: What is the total number of PG members in West Garo Hills? | D19: 1: All financial years combined | E19: data | F19: West Garo Hills has 21,867 PG members across all financial years. | G19: SELECT SUM(no_of_pg_members) AS memberships FROM curated.v_focus_legacy WHERE lgd_district = 'WEST GARO HILLS' LIMIT 1 | H19: 21,867 PG members in West Garo Hills | I19: 21,867 | J19: 21,867 | K19: MATCH | L19: MATCH | M19: PASS | N19: PASS | O19: PASS | P19: PASS | Q19: Correct. | R19: View proof
A20: TC-18 | B20: Calculate the total amount disbursed by district | C20: What is the total amount disbursed for East Khasi Hills? | D20: 2: Focus Legacy (producer group payments) > All financial years combined | E20: data | F20: The total amount disbursed for East Khasi Hills for Focus Legacy across all financial years is 54205000.00. | G20: SELECT SUM(amount_disbursed) AS amount_disbursed FROM curated.v_focus_legacy WHERE lgd_district = 'EAST KHASI HILLS' LIMIT 1 | H20: 54205000.00 (East Khasi Hills, all years) | I20: Rs 5,42,05,000 | J20: Rs 5,42,05,000 | K20: MATCH | L20: MATCH | M20: PASS | N20: PASS | O20: PASS | P20: PASS | Q20: Correct value. Presentation remark: printed as '54205000.00' with no Rs symbol or Indian digit grouping. | R20: View proof
A21: TC-19 | B21: Identify Producer Groups based on disbursed amount | C21: Which Producer Groups received more than ₹1,00,000? | D21: 0 | E21: data | F21: 541 producer groups match in total; the top 25 are shown below. Here are the 25 results: - PG-FOCUS-WKH-3565 / Nongprat Lynti / EASTERN WEST KHASI HILLS - payments: 2, memberships: 201, amount disbursed: 1,005,000, groups qualifying: 541 - PG-FOCUS-SWGH-780 / Doram Pg / SOUTH WEST GARO HILLS - payments: 2, memberships: 40, amount disbursed: 200,000, groups qualifying: 541 - PG-FOCUS-NGH-3003 / Rangsang / NORTH GARO HILLS - payments: 2, memberships: 40, amount disbursed: 200,000, groups qualifying: 541 - PG-FOCUS-EKH-2613 / Umtyrkhow Pg / EAST KHASI HILLS - payments: 2, memberships: 40, amount disbursed: 200,000, groups qualifying: 541 - PG-FOCUS-NGH-2508 / Evergreen Producer Group / NORTH GARO HILLS - payments: 2, memberships: 40, amount disbursed: 200,000, groups qualifying: 541 - PG-FOCUS-WKH-5956 / Iainehlang Pg / WEST KHASI HILLS - payments: 2, memberships: 38, amount disbursed: 190,000, groups qualifying: 541 - PG-FOCUS-WGH-20068 / Rangsang Producer Group / WEST GARO HILLS - payments: 2, memberships: 36, amount disbursed: 180,000, groups qualifying: 541 - PG-FOCUS-RB-3709 / Nongmahir Pg-1 / RI BHOI - payments: 2, memberships: 36, amount disbursed: 180,000, groups qualifying: 541 - PG-FOCUS-WKH-7584 / Treilang / WEST KHASI HILLS - payments: 2, memberships: 36, amount disbursed: 180,000, groups qualifying: 541 - PG-FOCUS-RB-18747 / Erifa-14 Producer Group Pynthor / RI BHOI - payments: 2, memberships: 35, amount disbursed: 175,000, groups qualifying: 541 - PG-FOCUS-WKH-661 | G21: SELECT pg_id, MAX(pg_name) AS pg_name, lgd_district, COUNT(*) AS payments, SUM(no_of_pg_members) AS memberships, SUM(amount_disbursed) AS amount_disbursed, COUNT(*) OVER () AS groups_qualifying FROM curated.v_focus_legacy GROUP BY pg_id, lgd_district HAVING SUM(amount_disbursed) > 100000 ORDER BY amount_disbursed DESC LIMIT 25 | H21: 541 PGs received > Rs 1,00,000; top 25 listed, highest Nongprat Lynti Rs 10,05,000 | I21: 541 PGs; max Rs 10,05,000 | J21: 541 PGs; max Rs 10,05,000 | K21: MATCH | L21: MATCH | M21: PASS | N21: PASS | O21: PASS | P21: PASS | Q21: Correct total (541) and every listed PG's amount checked in DB and raw. Remarks: only the top 25 are listed in the text (all 541 qualify); 'groups qualifying: 541' is repeated on each line (cosmetic). | R21: View proof
A22: TC-20 | B22: Retrieve remittances within a specific date range | C22: Show me all remittances made between April and June 2025. | D22: 1: Focus Legacy (producer group payments) | E22: data | F22: Focus Legacy shows 5,106 remittances made between April and June 2025. The total amount disbursed for this period was 95,440,000.00. | G22: SELECT COUNT(*) AS payments, SUM(amount_disbursed) AS amount_disbursed, MIN(date_of_remittance) AS first_payment, MAX(date_of_remittance) AS last_payment FROM curated.v_focus_legacy WHERE date_of_remittance >= DATE '2025-04-01' AND date_of_remittance < DATE '2025-07-01' LIMIT 1000 | H22: 5,106 remittances, Rs 95,440,000.00 (Apr-Jun 2025) | I22: 5,106 rows; Rs 9,54,40,000 | J22: 5,106 rows; Rs 9,54,40,000 | K22: MATCH | L22: MATCH | M22: PASS | N22: PASS | O22: PASS | P22: PASS | Q22: Correct count and amount. Remark: 'show me all remittances' is answered as a summary (count + total) rather than a 5,106-line listing - appropriate for a chat answer. | R22: View proof
... A31: TC-28blk | B31: Supplementary: same question, C&RD block chip | C31: How many Producer Groups are mapped to Songsak? | D31: 2: The Songsak C&RD block > All financial years combined | E31: data | F31: Songsak block has 344 Producer Groups mapped across all financial years. | G31: SELECT COUNT(DISTINCT pg_id) AS producer_groups FROM curated.v_focus_legacy WHERE lgd_block = 'SONGSAK' LIMIT 100 | H31: 344 PGs in Songsak block | I31: 344 | J31: 344 | K31: MATCH | L31: MATCH | M31: PASS | N31: PASS | O31: PASS | P31: PASS | Q31: Supplementary (not counted): the block chip of the same question also answers correctly. | R31: View proof

Sheet DB vs Raw Reconciliation
A1: Focus Legacy - DB (curated.v_focus_legacy) vs raw file (Focus Legacy to share to BLH.csv), 2026-09-29
A3: Check | B3: Raw CSV | C3: DB | D3: Difference (DB - Raw) | E3: Status | F3: Note
A4: Row count | B4: 14569 | C4: 14569 | D4: =C4-B4 -> 0 | E4: =IF(C4=B4,"MATCH",IF(ISNUMBER(SEARCH("name",A4)),"BY DESIGN","MISMATCH")) -> MATCH | F4: joined 1:1 on raw id = DB source_row_id; 0 rows only in one source
A5: Total amount disbursed (Rs) | B5: 510105000 | C5: 510105000 | D5: =C5-B5 -> 0 | E5: =IF(C5=B5,"MATCH",IF(ISNUMBER(SEARCH("name",A5)),"BY DESIGN","MISMATCH")) -> MATCH
A6: Total PG members (sum over payments) | B6: 102021 | C6: 102021 | D6: =C6-B6 -> 0 | E6: =IF(C6=B6,"MATCH",IF(ISNUMBER(SEARCH("name",A6)),"BY DESIGN","MISMATCH")) -> MATCH | F6: TC-10 / TC-16
A7: PG members, each PG counted once at its largest size | B7: 91446 | C7: 91446 | D7: =C7-B7 -> 0 | E7: =IF(C7=B7,"MATCH",IF(ISNUMBER(SEARCH("name",A7)),"BY DESIGN","MISMATCH")) -> MATCH | F7: alternative definition, see TC-10 remark
A8: Distinct pg_id | B8: 11906 | C8: 11906 | D8: =C8-B8 -> 0 | E8: =IF(C8=B8,"MATCH",IF(ISNUMBER(SEARCH("name",A8)),"BY DESIGN","MISMATCH")) -> MATCH | F8: TC-08 / TC-11
A9: PGs paid more than once | B9: 2655 | C9: 2655 | D9: =C9-B9 -> 0 | E9: =IF(C9=B9,"MATCH",IF(ISNUMBER(SEARCH("name",A9)),"BY DESIGN","MISMATCH")) -> MATCH | F9: TC-12
A10: Exact duplicate payment rows | B10: 0 | C10: 0 | D10: =C10-B10 -> 0 | E10: =IF(C10=B10,"MATCH",IF(ISNUMBER(SEARCH("name",A10)),"BY DESIGN","MISMATCH")) -> MATCH | F10: TC-12
A11: PGs with > 15 members | B11: 1047 | C11: 1047 | D11: =C11-B11 -> 0 | E11: =IF(C11=B11,"MATCH",IF(ISNUMBER(SEARCH("name",A11)),"BY DESIGN","MISMATCH")) -> MATCH | F11: TC-15
A12: PG members, West Garo Hills | B12: 21867 | C12: 21867 | D12: =C12-B12 -> 0 | E12: =IF(C12=B12,"MATCH",IF(ISNUMBER(SEARCH("name",A12)),"BY DESIGN","MISMATCH")) -> MATCH | F12: TC-17
A13: Amount, East Khasi Hills (Rs) | B13: 54205000 | C13: 54205000 | D13: =C13-B13 -> 0 | E13: =IF(C13=B13,"MATCH",IF(ISNUMBER(SEARCH("name",A13)),"BY DESIGN","MISMATCH")) -> MATCH | F13: TC-18
A14: PGs with total amount > Rs 1,00,000 | B14: 541 | C14: 541 | D14: =C14-B14 -> 0 | E14: =IF(C14=B14,"MATCH",IF(ISNUMBER(SEARCH("name",A14)),"BY DESIGN","MISMATCH")) -> MATCH | F14: TC-19
A15: Largest amount to one PG (Rs) | B15: 1005000 | C15: 1005000 | D15: =C15-B15 -> 0 | E15: =IF(C15=B15,"MATCH",IF(ISNUMBER(SEARCH("name",A15)),"BY DESIGN","MISMATCH")) -> MATCH | F15: TC-19
A16: Remittances Apr-Jun 2025 (rows) | B16: 5106 | C16: 5106 | D16: =C16-B16 -> 0 | E16: =IF(C16=B16,"MATCH",IF(ISNUMBER(SEARCH("name",A16)),"BY DESIGN","MISMATCH")) -> MATCH | F16: TC-20
A17: Remittances Apr-Jun 2025 (Rs) | B17: 95440000 | C17: 95440000 | D17: =C17-B17 -> 0 | E17: =IF(C17=B17,"MATCH",IF(ISNUMBER(SEARCH("name",A17)),"BY DESIGN","MISMATCH")) -> MATCH | F17: TC-20
... A56: Row-level: rows where pg name (exact text) differs | B56: 0 | C56: 1636 | D56: =C56-B56 -> 1636 | E56: =IF(C56=B56,"MATCH",IF(ISNUMBER(SEARCH("name",A56)),"BY DESIGN","MISMATCH")) -> BY DESIGN | F56: DB keeps one current name per pg_id (by design); raw has older spellings
A57: Rows with no block | B57: 88 | C57: 88 | D57: =C57-B57 -> 0 | E57: =IF(C57=B57,"MATCH",IF(ISNUMBER(SEARCH("name",A57)),"BY DESIGN","MISMATCH")) -> MATCH
A58: Rows with no constituency | B58: 1101 | C58: 1101 | D58: =C58-B58 -> 0 | E58: =IF(C58=B58,"MATCH",IF(ISNUMBER(SEARCH("name",A58)),"BY DESIGN","MISMATCH")) -> MATCH

Sheet Proof Screenshots
A1: TC-01 - Understand the FOCUS scheme - PASS
A48: TC-02 - Understand the scheme objective - PASS
A89: TC-03 - Understand beneficiary eligibility - PASS
A127: TC-04 - Understand Producer Groups - PASS
A160: TC-05 - Understand financial assistance - PASS
A197: TC-06 - Understand scheme support provided to Producer Groups - PASS
A226: TC-07 - Understand fund distribution - PASS
A267: TC-08 - Understand scheme coverage - PASS
A309: TC-09 - Get a scheme overview for official briefing - PASS
A356: TC-10 - Identify total beneficiaries in the FOCUS scheme - PASS
A410: TC-11 - Identify unique Producer Groups - PASS
A451: TC-12 - Identify duplicate Producer Groups - PASS
... A1136: TC-28blk - Supplementary: same question, C&RD block chip - PASS
